ztree/__init__.py
ztree/jvm_manager.py
ztree/tree.py
ztree-0.1.1.dist-info/METADATA
ztree-0.1.1.dist-info/WHEEL
ztree-0.1.1.dist-info/top_level.txt
ztree-0.1.1.dist-info/RECORD
