Metadata-Version: 2.4
Name: ztree
Version: 0.1.1
Summary: ZTree is a Python wrapper around a Java decision tree algorithm.
Author: Eric Cheng
Author-email: Eric R <you@example.com>
License: MIT
Classifier: Programming Language :: Python :: 3
Classifier: License :: OSI Approved :: MIT License
Classifier: Operating System :: OS Independent
Requires-Python: >=3.8
Requires-Dist: numpy
Requires-Dist: scikit-learn
Requires-Dist: jpype1
Dynamic: author
Dynamic: requires-python
